[{"drawTime":"2020072112223000","issue":"189975","jackpot":["1 666 327,50"],"numbers":"20,16,2,14,9,12,4,18|3","detail":[{"level":"8 + 1","total_winner":"0","wininrub":"0","numbersOfWinners":"0"},{"level":"8","total_winner":"0","wininrub":"0","numbersOfWinners":"0"},{"level":"7 + 1","total_winner":"0","wininrub":"0","numbersOfWinners":"0"},{"level":"7","total_winner":"0","wininrub":"0","numbersOfWinners":"0"},{"level":"6 + 1","total_winner":"45 000","wininrub":"4500","numbersOfWinners":"10"},{"level":"6","total_winner":"27 000","wininrub":"1500","numbersOfWinners":"18"},{"level":"5 + 1","total_winner":"37 500","wininrub":"750","numbersOfWinners":"50"},{"level":"5","total_winner":"39 900","wininrub":"300","numbersOfWinners":"133"},{"level":"4 + 1","total_winner":"14 850","wininrub":"150","numbersOfWinners":"99"}],"lotteryID":"ru-rapido","name":"rapido","other":[{"name":"Число билетов, принявших участие в розыгрыше,","value":"1457"},{"name":"Комбинаций","value":"1817"},{"name":"Общая сумма выигрышей, руб.","value":"164 250"},{"name":"Суперприз, руб.","value":"1 666 327,50"},{"name":"В архиве тиража отображается сумма суперприза на начало тиража, которая разыгрывалась в этом тираже.","value":""}]},{"drawTime":"2020072023073000","issue":"189925","jackpot":["1 766 962,50"],"numbers":"15,19,7,8,18,11,17,4|4","detail":[{"level":"8 + 1","total_winner":"0","wininrub":"0","numbersOfWinners":"0"},{"level":"8","total_winner":"0","wininrub":"0","numbersOfWinners":"0"},{"level":"7 + 1","total_winner":"0","wininrub":"0","numbersOfWinners":"0"},{"level":"7","total_winner":"0","wininrub":"0","numbersOfWinners":"0"},{"level":"6 + 1","total_winner":"27 000","wininrub":"4500","numbersOfWinners":"6"},{"level":"6","total_winner":"25 500","wininrub":"1500","numbersOfWinners":"17"},{"level":"5 + 1","total_winner":"36 750","wininrub":"750","numbersOfWinners":"49"},{"level":"5","total_winner":"34 200","wininrub":"300","numbersOfWinners":"114"},{"level":"4 + 1","total_winner":"12 150","wininrub":"150","numbersOfWinners":"81"}],"lotteryID":"ru-rapido","name":"rapido","other":[{"name":"Число билетов, принявших участие в розыгрыше,","value":"1051"},{"name":"Комбинаций","value":"1285"},{"name":"Общая сумма выигрышей, руб.","value":"135 600"},{"name":"Суперприз, руб.","value":"1 766 962,50"},{"name":"В архиве тиража отображается сумма суперприза на начало тиража, которая разыгрывалась в этом тираже.","value":""}]},{"drawTime":"2020072007373000","issue":"189875","jackpot":["1 199 574"],"numbers":"7,10,17,18,8,2,11,19|2","detail":[{"level":"8 + 1","total_winner":"0","wininrub":"0","numbersOfWinners":"0"},{"level":"8","total_winner":"0","wininrub":"0","numbersOfWinners":"0"},{"level":"7 + 1","total_winner":"0","wininrub":"0","numbersOfWinners":"0"},{"level":"7","total_winner":"0","wininrub":"0","numbersOfWinners":"0"},{"level":"6 + 1","total_winner":"18 000","wininrub":"4500","numbersOfWinners":"4"},{"level":"6","total_winner":"21 000","wininrub":"1500","numbersOfWinners":"14"},{"level":"5 + 1","total_winner":"15 750","wininrub":"750","numbersOfWinners":"21"},{"level":"5","total_winner":"19 200","wininrub":"300","numbersOfWinners":"64"},{"level":"4 + 1","total_winner":"9450","wininrub":"150","numbersOfWinners":"63"}],"lotteryID":"ru-rapido","name":"rapido","other":[{"name":"Число билетов, принявших участие в розыгрыше,","value":"594"},{"name":"Комбинаций","value":"732"},{"name":"Общая сумма выигрышей, руб.","value":"83 400"},{"name":"Суперприз, руб.","value":"1 199 574"},{"name":"В архиве тиража отображается сумма суперприза на начало тиража, которая разыгрывалась в этом тираже.","value":""}]},{"drawTime":"2020071918223000","issue":"189825","jackpot":["846 309"],"numbers":"6,14,15,5,2,16,18,4|4","detail":[{"level":"8 + 1","total_winner":"0","wininrub":"0","numbersOfWinners":"0"},{"level":"8","total_winner":"0","wininrub":"0","numbersOfWinners":"0"},{"level":"7 + 1","total_winner":"0","wininrub":"0","numbersOfWinners":"0"},{"level":"7","total_winner":"7500","wininrub":"7500","numbersOfWinners":"1"},{"level":"6 + 1","total_winner":"13 500","wininrub":"4500","numbersOfWinners":"3"},{"level":"6","total_winner":"7500","wininrub":"1500","numbersOfWinners":"5"},{"level":"5 + 1","total_winner":"20 250","wininrub":"750","numbersOfWinners":"27"},{"level":"5","total_winner":"35 100","wininrub":"300","numbersOfWinners":"117"},{"level":"4 + 1","total_winner":"11 550","wininrub":"150","numbersOfWinners":"77"}],"lotteryID":"ru-rapido","name":"rapido","other":[{"name":"Число билетов, принявших участие в розыгрыше,","value":"1076"},{"name":"Комбинаций","value":"1389"},{"name":"Общая сумма выигрышей, руб.","value":"95 400"},{"name":"Суперприз, руб.","value":"846 309"},{"name":"В архиве тиража отображается сумма суперприза на начало тиража, которая разыгрывалась в этом тираже.","value":""}]},{"drawTime":"2020071903373000","issue":"189775","jackpot":["200 000"],"numbers":"20,18,5,7,11,6,12,4|4","detail":[{"level":"8 + 1","total_winner":"0","wininrub":"0","numbersOfWinners":"0"},{"level":"8","total_winner":"0","wininrub":"0","numbersOfWinners":"0"},{"level":"7 + 1","total_winner":"0","wininrub":"0","numbersOfWinners":"0"},{"level":"7","total_winner":"0","wininrub":"0","numbersOfWinners":"0"},{"level":"6 + 1","total_winner":"0","wininrub":"0","numbersOfWinners":"0"},{"level":"6","total_winner":"3000","wininrub":"1500","numbersOfWinners":"2"},{"level":"5 + 1","total_winner":"3750","wininrub":"750","numbersOfWinners":"5"},{"level":"5","total_winner":"3600","wininrub":"300","numbersOfWinners":"12"},{"level":"4 + 1","total_winner":"2550","wininrub":"150","numbersOfWinners":"17"}],"lotteryID":"ru-rapido","name":"rapido","other":[{"name":"Число билетов, принявших участие в розыгрыше,","value":"147"},{"name":"Комбинаций","value":"250"},{"name":"Общая сумма выигрышей, руб.","value":"12 900"},{"name":"Суперприз, руб.","value":"200 000"},{"name":"В архиве тиража отображается сумма суперприза на начало тиража, которая разыгрывалась в этом тираже.","value":""}]},{"drawTime":"2020071813373000","issue":"189725","jackpot":["200 000"],"numbers":"7,18,20,4,15,11,1,19|1","detail":[{"level":"8 + 1","total_winner":"0","wininrub":"0","numbersOfWinners":"0"},{"level":"8","total_winner":"0","wininrub":"0","numbersOfWinners":"0"},{"level":"7 + 1","total_winner":"0","wininrub":"0","numbersOfWinners":"0"},{"level":"7","total_winner":"22 500","wininrub":"7500","numbersOfWinners":"3"},{"level":"6 + 1","total_winner":"72 000","wininrub":"4500","numbersOfWinners":"16"},{"level":"6","total_winner":"28 500","wininrub":"1500","numbersOfWinners":"19"},{"level":"5 + 1","total_winner":"48 000","wininrub":"750","numbersOfWinners":"64"},{"level":"5","total_winner":"60 600","wininrub":"300","numbersOfWinners":"202"},{"level":"4 + 1","total_winner":"19 800","wininrub":"150","numbersOfWinners":"132"}],"lotteryID":"ru-rapido","name":"rapido","other":[{"name":"Число билетов, принявших участие в розыгрыше,","value":"1831"},{"name":"Комбинаций","value":"2288"},{"name":"Общая сумма выигрышей, руб.","value":"251 400"},{"name":"Суперприз, руб.","value":"200 000"},{"name":"В архиве тиража отображается сумма суперприза на начало тиража, которая разыгрывалась в этом тираже.","value":""}]},{"drawTime":"2020071723373000","issue":"189675","jackpot":["200 000"],"numbers":"15,18,17,12,9,16,19,2|3","detail":[{"level":"8 + 1","total_winner":"0","wininrub":"0","numbersOfWinners":"0"},{"level":"8","total_winner":"0","wininrub":"0","numbersOfWinners":"0"},{"level":"7 + 1","total_winner":"0","wininrub":"0","numbersOfWinners":"0"},{"level":"7","total_winner":"0","wininrub":"0","numbersOfWinners":"0"},{"level":"6 + 1","total_winner":"31 500","wininrub":"4500","numbersOfWinners":"7"},{"level":"6","total_winner":"7500","wininrub":"1500","numbersOfWinners":"5"},{"level":"5 + 1","total_winner":"23 250","wininrub":"750","numbersOfWinners":"31"},{"level":"5","total_winner":"23 400","wininrub":"300","numbersOfWinners":"78"},{"level":"4 + 1","total_winner":"9600","wininrub":"150","numbersOfWinners":"64"}],"lotteryID":"ru-rapido","name":"rapido","other":[{"name":"Число билетов, принявших участие в розыгрыше,","value":"679"},{"name":"Комбинаций","value":"867"},{"name":"Общая сумма выигрышей, руб.","value":"95 250"},{"name":"Суперприз, руб.","value":"200 000"},{"name":"В архиве тиража отображается сумма суперприза на начало тиража, которая разыгрывалась в этом тираже.","value":""}]},{"drawTime":"2020071708073000","issue":"189625","jackpot":["7 900 294,50"],"numbers":"12,9,8,11,2,16,14,19|1","detail":[{"level":"8 + 1","total_winner":"0","wininrub":"0","numbersOfWinners":"0"},{"level":"8","total_winner":"0","wininrub":"0","numbersOfWinners":"0"},{"level":"7 + 1","total_winner":"45 000","wininrub":"22 500","numbersOfWinners":"2"},{"level":"7","total_winner":"0","wininrub":"0","numbersOfWinners":"0"},{"level":"6 + 1","total_winner":"31 500","wininrub":"4500","numbersOfWinners":"7"},{"level":"6","total_winner":"34 500","wininrub":"1500","numbersOfWinners":"23"},{"level":"5 + 1","total_winner":"27 750","wininrub":"750","numbersOfWinners":"37"},{"level":"5","total_winner":"43 200","wininrub":"300","numbersOfWinners":"144"},{"level":"4 + 1","total_winner":"19 800","wininrub":"150","numbersOfWinners":"132"}],"lotteryID":"ru-rapido","name":"rapido","other":[{"name":"Число билетов, принявших участие в розыгрыше,","value":"1661"},{"name":"Комбинаций","value":"2068"},{"name":"Общая сумма выигрышей, руб.","value":"201 750"},{"name":"Суперприз, руб.","value":"7 900 294,50"},{"name":"В архиве тиража отображается сумма суперприза на начало тиража, которая разыгрывалась в этом тираже.","value":""}]},{"drawTime":"2020071618523000","issue":"189575","jackpot":["7 373 385"],"numbers":"20,3,5,15,17,10,12,18|1","detail":[{"level":"8 + 1","total_winner":"0","wininrub":"0","numbersOfWinners":"0"},{"level":"8","total_winner":"0","wininrub":"0","numbersOfWinners":"0"},{"level":"7 + 1","total_winner":"22 500","wininrub":"22 500","numbersOfWinners":"1"},{"level":"7","total_winner":"7500","wininrub":"7500","numbersOfWinners":"1"},{"level":"6 + 1","total_winner":"36 000","wininrub":"4500","numbersOfWinners":"8"},{"level":"6","total_winner":"63 000","wininrub":"1500","numbersOfWinners":"42"},{"level":"5 + 1","total_winner":"65 250","wininrub":"750","numbersOfWinners":"87"},{"level":"5","total_winner":"73 500","wininrub":"300","numbersOfWinners":"245"},{"level":"4 + 1","total_winner":"30 150","wininrub":"150","numbersOfWinners":"201"}],"lotteryID":"ru-rapido","name":"rapido","other":[{"name":"Число билетов, принявших участие в розыгрыше,","value":"2617"},{"name":"Комбинаций","value":"3245"},{"name":"Общая сумма выигрышей, руб.","value":"297 900"},{"name":"Суперприз, руб.","value":"7 373 385"},{"name":"В архиве тиража отображается сумма суперприза на начало тиража, которая разыгрывалась в этом тираже.","value":""}]},{"drawTime":"2020071604073000","issue":"189525","jackpot":["6 434 082"],"numbers":"12,15,5,17,9,4,10,18|3","detail":[{"level":"8 + 1","total_winner":"0","wininrub":"0","numbersOfWinners":"0"},{"level":"8","total_winner":"0","wininrub":"0","numbersOfWinners":"0"},{"level":"7 + 1","total_winner":"0","wininrub":"0","numbersOfWinners":"0"},{"level":"7","total_winner":"7500","wininrub":"7500","numbersOfWinners":"1"},{"level":"6 + 1","total_winner":"9000","wininrub":"4500","numbersOfWinners":"2"},{"level":"6","total_winner":"6000","wininrub":"1500","numbersOfWinners":"4"},{"level":"5 + 1","total_winner":"13 500","wininrub":"750","numbersOfWinners":"18"},{"level":"5","total_winner":"12 300","wininrub":"300","numbersOfWinners":"41"},{"level":"4 + 1","total_winner":"6000","wininrub":"150","numbersOfWinners":"40"}],"lotteryID":"ru-rapido","name":"rapido","other":[{"name":"Число билетов, принявших участие в розыгрыше,","value":"404"},{"name":"Комбинаций","value":"483"},{"name":"Общая сумма выигрышей, руб.","value":"54 300"},{"name":"Суперприз, руб.","value":"6 434 082"},{"name":"В архиве тиража отображается сумма суперприза на начало тиража, которая разыгрывалась в этом тираже.","value":""}]},{"drawTime":"2020071514073000","issue":"189475","jackpot":["5 302 384,50"],"numbers":"2,11,10,15,14,4,16,5|1","detail":[{"level":"8 + 1","total_winner":"0","wininrub":"0","numbersOfWinners":"0"},{"level":"8","total_winner":"0","wininrub":"0","numbersOfWinners":"0"},{"level":"7 + 1","total_winner":"22 500","wininrub":"22 500","numbersOfWinners":"1"},{"level":"7","total_winner":"7500","wininrub":"7500","numbersOfWinners":"1"},{"level":"6 + 1","total_winner":"36 000","wininrub":"4500","numbersOfWinners":"8"},{"level":"6","total_winner":"43 500","wininrub":"1500","numbersOfWinners":"29"},{"level":"5 + 1","total_winner":"59 250","wininrub":"750","numbersOfWinners":"79"},{"level":"5","total_winner":"71 700","wininrub":"300","numbersOfWinners":"239"},{"level":"4 + 1","total_winner":"26 850","wininrub":"150","numbersOfWinners":"179"}],"lotteryID":"ru-rapido","name":"rapido","other":[{"name":"Число билетов, принявших участие в розыгрыше,","value":"2173"},{"name":"Комбинаций","value":"2843"},{"name":"Общая сумма выигрышей, руб.","value":"267 300"},{"name":"Суперприз, руб.","value":"5 302 384,50"},{"name":"В архиве тиража отображается сумма суперприза на начало тиража, которая разыгрывалась в этом тираже.","value":""}]},{"drawTime":"2020071500073000","issue":"189425","jackpot":["4 720 546,50"],"numbers":"5,12,8,10,20,16,4,7|2","detail":[{"level":"8 + 1","total_winner":"0","wininrub":"0","numbersOfWinners":"0"},{"level":"8","total_winner":"0","wininrub":"0","numbersOfWinners":"0"},{"level":"7 + 1","total_winner":"0","wininrub":"0","numbersOfWinners":"0"},{"level":"7","total_winner":"15 000","wininrub":"7500","numbersOfWinners":"2"},{"level":"6 + 1","total_winner":"18 000","wininrub":"4500","numbersOfWinners":"4"},{"level":"6","total_winner":"36 000","wininrub":"1500","numbersOfWinners":"24"},{"level":"5 + 1","total_winner":"27 750","wininrub":"750","numbersOfWinners":"37"},{"level":"5","total_winner":"32 700","wininrub":"300","numbersOfWinners":"109"},{"level":"4 + 1","total_winner":"18 000","wininrub":"150","numbersOfWinners":"120"}],"lotteryID":"ru-rapido","name":"rapido","other":[{"name":"Число билетов, принявших участие в розыгрыше,","value":"1154"},{"name":"Комбинаций","value":"1570"},{"name":"Общая сумма выигрышей, руб.","value":"147 450"},{"name":"Суперприз, руб.","value":"4 720 546,50"},{"name":"В архиве тиража отображается сумма суперприза на начало тиража, которая разыгрывалась в этом тираже.","value":""}]},{"drawTime":"2020071408373000","issue":"189375","jackpot":["4 548 754,50"],"numbers":"15,2,18,11,13,12,3,1|4","detail":[{"level":"8 + 1","total_winner":"0","wininrub":"0","numbersOfWinners":"0"},{"level":"8","total_winner":"0","wininrub":"0","numbersOfWinners":"0"},{"level":"7 + 1","total_winner":"22 500","wininrub":"22 500","numbersOfWinners":"1"},{"level":"7","total_winner":"0","wininrub":"0","numbersOfWinners":"0"},{"level":"6 + 1","total_winner":"9000","wininrub":"4500","numbersOfWinners":"2"},{"level":"6","total_winner":"7500","wininrub":"1500","numbersOfWinners":"5"},{"level":"5 + 1","total_winner":"23 250","wininrub":"750","numbersOfWinners":"31"},{"level":"5","total_winner":"33 300","wininrub":"300","numbersOfWinners":"111"},{"level":"4 + 1","total_winner":"14 550","wininrub":"150","numbersOfWinners":"97"}],"lotteryID":"ru-rapido","name":"rapido","other":[{"name":"Число билетов, принявших участие в розыгрыше,","value":"1349"},{"name":"Комбинаций","value":"1636"},{"name":"Общая сумма выигрышей, руб.","value":"110 100"},{"name":"Суперприз, руб.","value":"4 548 754,50"},{"name":"В архиве тиража отображается сумма суперприза на начало тиража, которая разыгрывалась в этом тираже.","value":""}]},{"drawTime":"2020071319223000","issue":"189325","jackpot":["3 742 665"],"numbers":"19,9,17,8,6,1,18,4|4","detail":[{"level":"8 + 1","total_winner":"0","wininrub":"0","numbersOfWinners":"0"},{"level":"8","total_winner":"0","wininrub":"0","numbersOfWinners":"0"},{"level":"7 + 1","total_winner":"0","wininrub":"0","numbersOfWinners":"0"},{"level":"7","total_winner":"7500","wininrub":"7500","numbersOfWinners":"1"},{"level":"6 + 1","total_winner":"27 000","wininrub":"4500","numbersOfWinners":"6"},{"level":"6","total_winner":"37 500","wininrub":"1500","numbersOfWinners":"25"},{"level":"5 + 1","total_winner":"41 250","wininrub":"750","numbersOfWinners":"55"},{"level":"5","total_winner":"59 100","wininrub":"300","numbersOfWinners":"197"},{"level":"4 + 1","total_winner":"21 000","wininrub":"150","numbersOfWinners":"140"}],"lotteryID":"ru-rapido","name":"rapido","other":[{"name":"Число билетов, принявших участие в розыгрыше,","value":"1910"},{"name":"Комбинаций","value":"2363"},{"name":"Общая сумма выигрышей, руб.","value":"193 350"},{"name":"Суперприз, руб.","value":"3 742 665"},{"name":"В архиве тиража отображается сумма суперприза на начало тиража, которая разыгрывалась в этом тираже.","value":""}]},{"drawTime":"2020071304373000","issue":"189275","jackpot":["2 937 705"],"numbers":"19,20,11,2,8,9,14,10|2","detail":[{"level":"8 + 1","total_winner":"0","wininrub":"0","numbersOfWinners":"0"},{"level":"8","total_winner":"0","wininrub":"0","numbersOfWinners":"0"},{"level":"7 + 1","total_winner":"0","wininrub":"0","numbersOfWinners":"0"},{"level":"7","total_winner":"0","wininrub":"0","numbersOfWinners":"0"},{"level":"6 + 1","total_winner":"4500","wininrub":"4500","numbersOfWinners":"1"},{"level":"6","total_winner":"3000","wininrub":"1500","numbersOfWinners":"2"},{"level":"5 + 1","total_winner":"5250","wininrub":"750","numbersOfWinners":"7"},{"level":"5","total_winner":"6300","wininrub":"300","numbersOfWinners":"21"},{"level":"4 + 1","total_winner":"1650","wininrub":"150","numbersOfWinners":"11"}],"lotteryID":"ru-rapido","name":"rapido","other":[{"name":"Число билетов, принявших участие в розыгрыше,","value":"299"},{"name":"Комбинаций","value":"346"},{"name":"Общая сумма выигрышей, руб.","value":"20 700"},{"name":"Суперприз, руб.","value":"2 937 705"},{"name":"В архиве тиража отображается сумма суперприза на начало тиража, которая разыгрывалась в этом тираже.","value":""}]},{"drawTime":"2020071214373000","issue":"189225","jackpot":["2 239 015,50"],"numbers":"8,3,16,20,19,9,15,10|1","detail":[{"level":"8 + 1","total_winner":"0","wininrub":"0","numbersOfWinners":"0"},{"level":"8","total_winner":"0","wininrub":"0","numbersOfWinners":"0"},{"level":"7 + 1","total_winner":"0","wininrub":"0","numbersOfWinners":"0"},{"level":"7","total_winner":"7500","wininrub":"7500","numbersOfWinners":"1"},{"level":"6 + 1","total_winner":"0","wininrub":"0","numbersOfWinners":"0"},{"level":"6","total_winner":"28 500","wininrub":"1500","numbersOfWinners":"19"},{"level":"5 + 1","total_winner":"32 250","wininrub":"750","numbersOfWinners":"43"},{"level":"5","total_winner":"42 900","wininrub":"300","numbersOfWinners":"143"},{"level":"4 + 1","total_winner":"18 300","wininrub":"150","numbersOfWinners":"122"}],"lotteryID":"ru-rapido","name":"rapido","other":[{"name":"Число билетов, принявших участие в розыгрыше,","value":"1531"},{"name":"Комбинаций","value":"1936"},{"name":"Общая сумма выигрышей, руб.","value":"129 450"},{"name":"Суперприз, руб.","value":"2 239 015,50"},{"name":"В архиве тиража отображается сумма суперприза на начало тиража, которая разыгрывалась в этом тираже.","value":""}]},{"drawTime":"2020071200373000","issue":"189175","jackpot":["1 769 926,50"],"numbers":"13,1,7,9,18,10,4,14|4","detail":[{"level":"8 + 1","total_winner":"0","wininrub":"0","numbersOfWinners":"0"},{"level":"8","total_winner":"0","wininrub":"0","numbersOfWinners":"0"},{"level":"7 + 1","total_winner":"0","wininrub":"0","numbersOfWinners":"0"},{"level":"7","total_winner":"0","wininrub":"0","numbersOfWinners":"0"},{"level":"6 + 1","total_winner":"0","wininrub":"0","numbersOfWinners":"0"},{"level":"6","total_winner":"9000","wininrub":"1500","numbersOfWinners":"6"},{"level":"5 + 1","total_winner":"9750","wininrub":"750","numbersOfWinners":"13"},{"level":"5","total_winner":"21 600","wininrub":"300","numbersOfWinners":"72"},{"level":"4 + 1","total_winner":"8400","wininrub":"150","numbersOfWinners":"56"}],"lotteryID":"ru-rapido","name":"rapido","other":[{"name":"Число билетов, принявших участие в розыгрыше,","value":"595"},{"name":"Комбинаций","value":"732"},{"name":"Общая сумма выигрышей, руб.","value":"48 750"},{"name":"Суперприз, руб.","value":"1 769 926,50"},{"name":"В архиве тиража отображается сумма суперприза на начало тиража, которая разыгрывалась в этом тираже.","value":""}]},{"drawTime":"2020071109073000","issue":"189125","jackpot":["1 809 928,50"],"numbers":"11,10,19,3,5,17,8,16|4","detail":[{"level":"8 + 1","total_winner":"0","wininrub":"0","numbersOfWinners":"0"},{"level":"8","total_winner":"0","wininrub":"0","numbersOfWinners":"0"},{"level":"7 + 1","total_winner":"0","wininrub":"0","numbersOfWinners":"0"},{"level":"7","total_winner":"7500","wininrub":"7500","numbersOfWinners":"1"},{"level":"6 + 1","total_winner":"22 500","wininrub":"4500","numbersOfWinners":"5"},{"level":"6","total_winner":"22 500","wininrub":"1500","numbersOfWinners":"15"},{"level":"5 + 1","total_winner":"15 000","wininrub":"750","numbersOfWinners":"20"},{"level":"5","total_winner":"32 100","wininrub":"300","numbersOfWinners":"107"},{"level":"4 + 1","total_winner":"13 200","wininrub":"150","numbersOfWinners":"88"}],"lotteryID":"ru-rapido","name":"rapido","other":[{"name":"Число билетов, принявших участие в розыгрыше,","value":"1044"},{"name":"Комбинаций","value":"1294"},{"name":"Общая сумма выигрышей, руб.","value":"112 800"},{"name":"Суперприз, руб.","value":"1 809 928,50"},{"name":"В архиве тиража отображается сумма суперприза на начало тиража, которая разыгрывалась в этом тираже.","value":""}]},{"drawTime":"2020071019523000","issue":"189075","jackpot":["1 721 136"],"numbers":"11,7,12,16,10,8,18,5|2","detail":[{"level":"8 + 1","total_winner":"0","wininrub":"0","numbersOfWinners":"0"},{"level":"8","total_winner":"0","wininrub":"0","numbersOfWinners":"0"},{"level":"7 + 1","total_winner":"22 500","wininrub":"22 500","numbersOfWinners":"1"},{"level":"7","total_winner":"0","wininrub":"0","numbersOfWinners":"0"},{"level":"6 + 1","total_winner":"27 000","wininrub":"4500","numbersOfWinners":"6"},{"level":"6","total_winner":"19 500","wininrub":"1500","numbersOfWinners":"13"},{"level":"5 + 1","total_winner":"26 250","wininrub":"750","numbersOfWinners":"35"},{"level":"5","total_winner":"54 300","wininrub":"300","numbersOfWinners":"181"},{"level":"4 + 1","total_winner":"24 000","wininrub":"150","numbersOfWinners":"160"}],"lotteryID":"ru-rapido","name":"rapido","other":[{"name":"Число билетов, принявших участие в розыгрыше,","value":"1433"},{"name":"Комбинаций","value":"1895"},{"name":"Общая сумма выигрышей, руб.","value":"173 550"},{"name":"Суперприз, руб.","value":"1 721 136"},{"name":"В архиве тиража отображается сумма суперприза на начало тиража, которая разыгрывалась в этом тираже.","value":""}]},{"drawTime":"2020071005073000","issue":"189025","jackpot":["999 904,50"],"numbers":"14,1,15,11,16,13,9,7|3","detail":[{"level":"8 + 1","total_winner":"0","wininrub":"0","numbersOfWinners":"0"},{"level":"8","total_winner":"0","wininrub":"0","numbersOfWinners":"0"},{"level":"7 + 1","total_winner":"0","wininrub":"0","numbersOfWinners":"0"},{"level":"7","total_winner":"0","wininrub":"0","numbersOfWinners":"0"},{"level":"6 + 1","total_winner":"4500","wininrub":"4500","numbersOfWinners":"1"},{"level":"6","total_winner":"10 500","wininrub":"1500","numbersOfWinners":"7"},{"level":"5 + 1","total_winner":"3750","wininrub":"750","numbersOfWinners":"5"},{"level":"5","total_winner":"8400","wininrub":"300","numbersOfWinners":"28"},{"level":"4 + 1","total_winner":"4500","wininrub":"150","numbersOfWinners":"30"}],"lotteryID":"ru-rapido","name":"rapido","other":[{"name":"Число билетов, принявших участие в розыгрыше,","value":"302"},{"name":"Комбинаций","value":"428"},{"name":"Общая сумма выигрышей, руб.","value":"31 650"},{"name":"Суперприз, руб.","value":"999 904,50"},{"name":"В архиве тиража отображается сумма суперприза на начало тиража, которая разыгрывалась в этом тираже.","value":""}]},{"drawTime":"2020070915073000","issue":"188975","jackpot":["443 272,50"],"numbers":"9,7,6,19,14,15,20,1|3","detail":[{"level":"8 + 1","total_winner":"0","wininrub":"0","numbersOfWinners":"0"},{"level":"8","total_winner":"0","wininrub":"0","numbersOfWinners":"0"},{"level":"7 + 1","total_winner":"0","wininrub":"0","numbersOfWinners":"0"},{"level":"7","total_winner":"0","wininrub":"0","numbersOfWinners":"0"},{"level":"6 + 1","total_winner":"9000","wininrub":"4500","numbersOfWinners":"2"},{"level":"6","total_winner":"42 000","wininrub":"1500","numbersOfWinners":"28"},{"level":"5 + 1","total_winner":"23 250","wininrub":"750","numbersOfWinners":"31"},{"level":"5","total_winner":"21 000","wininrub":"300","numbersOfWinners":"70"},{"level":"4 + 1","total_winner":"17 100","wininrub":"150","numbersOfWinners":"114"}],"lotteryID":"ru-rapido","name":"rapido","other":[{"name":"Число билетов, принявших участие в розыгрыше,","value":"1093"},{"name":"Комбинаций","value":"1366"},{"name":"Общая сумма выигрышей, руб.","value":"112 350"},{"name":"Суперприз, руб.","value":"443 272,50"},{"name":"В архиве тиража отображается сумма суперприза на начало тиража, которая разыгрывалась в этом тираже.","value":""}]},{"drawTime":"2020070901073000","issue":"188925","jackpot":["200 000"],"numbers":"1,13,8,9,12,7,19,4|4","detail":[{"level":"8 + 1","total_winner":"0","wininrub":"0","numbersOfWinners":"0"},{"level":"8","total_winner":"0","wininrub":"0","numbersOfWinners":"0"},{"level":"7 + 1","total_winner":"0","wininrub":"0","numbersOfWinners":"0"},{"level":"7","total_winner":"0","wininrub":"0","numbersOfWinners":"0"},{"level":"6 + 1","total_winner":"4500","wininrub":"4500","numbersOfWinners":"1"},{"level":"6","total_winner":"3000","wininrub":"1500","numbersOfWinners":"2"},{"level":"5 + 1","total_winner":"6000","wininrub":"750","numbersOfWinners":"8"},{"level":"5","total_winner":"11 400","wininrub":"300","numbersOfWinners":"38"},{"level":"4 + 1","total_winner":"4800","wininrub":"150","numbersOfWinners":"32"}],"lotteryID":"ru-rapido","name":"rapido","other":[{"name":"Число билетов, принявших участие в розыгрыше,","value":"257"},{"name":"Комбинаций","value":"371"},{"name":"Общая сумма выигрышей, руб.","value":"29 700"},{"name":"Суперприз, руб.","value":"200 000"},{"name":"В архиве тиража отображается сумма суперприза на начало тиража, которая разыгрывалась в этом тираже.","value":""}]},{"drawTime":"2020070809373000","issue":"188875","jackpot":["8 341 026"],"numbers":"1,16,12,14,18,17,2,3|1","detail":[{"level":"8 + 1","total_winner":"0","wininrub":"0","numbersOfWinners":"0"},{"level":"8","total_winner":"0","wininrub":"0","numbersOfWinners":"0"},{"level":"7 + 1","total_winner":"0","wininrub":"0","numbersOfWinners":"0"},{"level":"7","total_winner":"0","wininrub":"0","numbersOfWinners":"0"},{"level":"6 + 1","total_winner":"18 000","wininrub":"4500","numbersOfWinners":"4"},{"level":"6","total_winner":"13 500","wininrub":"1500","numbersOfWinners":"9"},{"level":"5 + 1","total_winner":"25 500","wininrub":"750","numbersOfWinners":"34"},{"level":"5","total_winner":"36 600","wininrub":"300","numbersOfWinners":"122"},{"level":"4 + 1","total_winner":"15 000","wininrub":"150","numbersOfWinners":"100"}],"lotteryID":"ru-rapido","name":"rapido","other":[{"name":"Число билетов, принявших участие в розыгрыше,","value":"1702"},{"name":"Комбинаций","value":"2080"},{"name":"Общая сумма выигрышей, руб.","value":"108 600"},{"name":"Суперприз, руб.","value":"8 341 026"},{"name":"В архиве тиража отображается сумма суперприза на начало тиража, которая разыгрывалась в этом тираже.","value":""}]},{"drawTime":"2020070720223000","issue":"188825","jackpot":["7 593 874,50"],"numbers":"17,16,9,11,18,10,15,3|1","detail":[{"level":"8 + 1","total_winner":"0","wininrub":"0","numbersOfWinners":"0"},{"level":"8","total_winner":"0","wininrub":"0","numbersOfWinners":"0"},{"level":"7 + 1","total_winner":"22 500","wininrub":"22 500","numbersOfWinners":"1"},{"level":"7","total_winner":"15 000","wininrub":"7500","numbersOfWinners":"2"},{"level":"6 + 1","total_winner":"13 500","wininrub":"4500","numbersOfWinners":"3"},{"level":"6","total_winner":"42 000","wininrub":"1500","numbersOfWinners":"28"},{"level":"5 + 1","total_winner":"39 750","wininrub":"750","numbersOfWinners":"53"},{"level":"5","total_winner":"61 200","wininrub":"300","numbersOfWinners":"204"},{"level":"4 + 1","total_winner":"25 350","wininrub":"150","numbersOfWinners":"169"}],"lotteryID":"ru-rapido","name":"rapido","other":[{"name":"Число билетов, принявших участие в розыгрыше,","value":"2078"},{"name":"Комбинаций","value":"2709"},{"name":"Общая сумма выигрышей, руб.","value":"219 300"},{"name":"Суперприз, руб.","value":"7 593 874,50"},{"name":"В архиве тиража отображается сумма суперприза на начало тиража, которая разыгрывалась в этом тираже.","value":""}]},{"drawTime":"2020070705373000","issue":"188775","jackpot":["6 459 634,50"],"numbers":"13,18,2,3,12,8,19,6|3","detail":[{"level":"8 + 1","total_winner":"0","wininrub":"0","numbersOfWinners":"0"},{"level":"8","total_winner":"0","wininrub":"0","numbersOfWinners":"0"},{"level":"7 + 1","total_winner":"0","wininrub":"0","numbersOfWinners":"0"},{"level":"7","total_winner":"0","wininrub":"0","numbersOfWinners":"0"},{"level":"6 + 1","total_winner":"27 000","wininrub":"4500","numbersOfWinners":"6"},{"level":"6","total_winner":"7500","wininrub":"1500","numbersOfWinners":"5"},{"level":"5 + 1","total_winner":"9000","wininrub":"750","numbersOfWinners":"12"},{"level":"5","total_winner":"15 300","wininrub":"300","numbersOfWinners":"51"},{"level":"4 + 1","total_winner":"7500","wininrub":"150","numbersOfWinners":"50"}],"lotteryID":"ru-rapido","name":"rapido","other":[{"name":"Число билетов, принявших участие в розыгрыше,","value":"571"},{"name":"Комбинаций","value":"709"},{"name":"Общая сумма выигрышей, руб.","value":"66 300"},{"name":"Суперприз, руб.","value":"6 459 634,50"},{"name":"В архиве тиража отображается сумма суперприза на начало тиража, которая разыгрывалась в этом тираже.","value":""}]},{"drawTime":"2020070615373000","issue":"188725","jackpot":["5 882 998,50"],"numbers":"2,17,16,7,11,15,5,3|4","detail":[{"level":"8 + 1","total_winner":"0","wininrub":"0","numbersOfWinners":"0"},{"level":"8","total_winner":"0","wininrub":"0","numbersOfWinners":"0"},{"level":"7 + 1","total_winner":"22 500","wininrub":"22 500","numbersOfWinners":"1"},{"level":"7","total_winner":"7500","wininrub":"7500","numbersOfWinners":"1"},{"level":"6 + 1","total_winner":"85 500","wininrub":"4500","numbersOfWinners":"19"},{"level":"6","total_winner":"79 500","wininrub":"1500","numbersOfWinners":"53"},{"level":"5 + 1","total_winner":"54 750","wininrub":"750","numbersOfWinners":"73"},{"level":"5","total_winner":"72 600","wininrub":"300","numbersOfWinners":"242"},{"level":"4 + 1","total_winner":"23 850","wininrub":"150","numbersOfWinners":"159"}],"lotteryID":"ru-rapido","name":"rapido","other":[{"name":"Число билетов, принявших участие в розыгрыше,","value":"1999"},{"name":"Комбинаций","value":"2550"},{"name":"Общая сумма выигрышей, руб.","value":"346 200"},{"name":"Суперприз, руб.","value":"5 882 998,50"},{"name":"В архиве тиража отображается сумма суперприза на начало тиража, которая разыгрывалась в этом тираже.","value":""}]},{"drawTime":"2020070601373000","issue":"188675","jackpot":["4 856 902,50"],"numbers":"1,3,4,8,14,5,11,12|1","detail":[{"level":"8 + 1","total_winner":"0","wininrub":"0","numbersOfWinners":"0"},{"level":"8","total_winner":"0","wininrub":"0","numbersOfWinners":"0"},{"level":"7 + 1","total_winner":"0","wininrub":"0","numbersOfWinners":"0"},{"level":"7","total_winner":"0","wininrub":"0","numbersOfWinners":"0"},{"level":"6 + 1","total_winner":"4500","wininrub":"4500","numbersOfWinners":"1"},{"level":"6","total_winner":"6000","wininrub":"1500","numbersOfWinners":"4"},{"level":"5 + 1","total_winner":"9000","wininrub":"750","numbersOfWinners":"12"},{"level":"5","total_winner":"9300","wininrub":"300","numbersOfWinners":"31"},{"level":"4 + 1","total_winner":"5250","wininrub":"150","numbersOfWinners":"35"}],"lotteryID":"ru-rapido","name":"rapido","other":[{"name":"Число билетов, принявших участие в розыгрыше,","value":"427"},{"name":"Комбинаций","value":"573"},{"name":"Общая сумма выигрышей, руб.","value":"34 050"},{"name":"Суперприз, руб.","value":"4 856 902,50"},{"name":"В архиве тиража отображается сумма суперприза на начало тиража, которая разыгрывалась в этом тираже.","value":""}]},{"drawTime":"2020070510523000","issue":"188625","jackpot":["3 564 445,50"],"numbers":"14,17,4,10,11,7,15,6|3","detail":[{"level":"8 + 1","total_winner":"0","wininrub":"0","numbersOfWinners":"0"},{"level":"8","total_winner":"0","wininrub":"0","numbersOfWinners":"0"},{"level":"7 + 1","total_winner":"0","wininrub":"0","numbersOfWinners":"0"},{"level":"7","total_winner":"0","wininrub":"0","numbersOfWinners":"0"},{"level":"6 + 1","total_winner":"27 000","wininrub":"4500","numbersOfWinners":"6"},{"level":"6","total_winner":"40 500","wininrub":"1500","numbersOfWinners":"27"},{"level":"5 + 1","total_winner":"69 750","wininrub":"750","numbersOfWinners":"93"},{"level":"5","total_winner":"49 200","wininrub":"300","numbersOfWinners":"164"},{"level":"4 + 1","total_winner":"32 550","wininrub":"150","numbersOfWinners":"217"}],"lotteryID":"ru-rapido","name":"rapido","other":[{"name":"Число билетов, принявших участие в розыгрыше,","value":"1739"},{"name":"Комбинаций","value":"2276"},{"name":"Общая сумма выигрышей, руб.","value":"219 000"},{"name":"Суперприз, руб.","value":"3 564 445,50"},{"name":"В архиве тиража отображается сумма суперприза на начало тиража, которая разыгрывалась в этом тираже.","value":""}]},{"drawTime":"2020070420523000","issue":"188575","jackpot":["3 351 358,50"],"numbers":"6,4,17,18,7,1,12,8|1","detail":[{"level":"8 + 1","total_winner":"0","wininrub":"0","numbersOfWinners":"0"},{"level":"8","total_winner":"0","wininrub":"0","numbersOfWinners":"0"},{"level":"7 + 1","total_winner":"0","wininrub":"0","numbersOfWinners":"0"},{"level":"7","total_winner":"0","wininrub":"0","numbersOfWinners":"0"},{"level":"6 + 1","total_winner":"27 000","wininrub":"4500","numbersOfWinners":"6"},{"level":"6","total_winner":"9000","wininrub":"1500","numbersOfWinners":"6"},{"level":"5 + 1","total_winner":"36 750","wininrub":"750","numbersOfWinners":"49"},{"level":"5","total_winner":"27 000","wininrub":"300","numbersOfWinners":"90"},{"level":"4 + 1","total_winner":"16 200","wininrub":"150","numbersOfWinners":"108"}],"lotteryID":"ru-rapido","name":"rapido","other":[{"name":"Число билетов, принявших участие в розыгрыше,","value":"1189"},{"name":"Комбинаций","value":"1548"},{"name":"Общая сумма выигрышей, руб.","value":"115 950"},{"name":"Суперприз, руб.","value":"3 351 358,50"},{"name":"В архиве тиража отображается сумма суперприза на начало тиража, которая разыгрывалась в этом тираже.","value":""}]},{"drawTime":"2020070406073000","issue":"188525","jackpot":["2 687 095,50"],"numbers":"14,19,2,5,9,20,18,15|1","detail":[{"level":"8 + 1","total_winner":"0","wininrub":"0","numbersOfWinners":"0"},{"level":"8","total_winner":"0","wininrub":"0","numbersOfWinners":"0"},{"level":"7 + 1","total_winner":"22 500","wininrub":"22 500","numbersOfWinners":"1"},{"level":"7","total_winner":"0","wininrub":"0","numbersOfWinners":"0"},{"level":"6 + 1","total_winner":"9000","wininrub":"4500","numbersOfWinners":"2"},{"level":"6","total_winner":"10 500","wininrub":"1500","numbersOfWinners":"7"},{"level":"5 + 1","total_winner":"8250","wininrub":"750","numbersOfWinners":"11"},{"level":"5","total_winner":"13 800","wininrub":"300","numbersOfWinners":"46"},{"level":"4 + 1","total_winner":"5700","wininrub":"150","numbersOfWinners":"38"}],"lotteryID":"ru-rapido","name":"rapido","other":[{"name":"Число билетов, принявших участие в розыгрыше,","value":"535"},{"name":"Комбинаций","value":"668"},{"name":"Общая сумма выигрышей, руб.","value":"69 750"},{"name":"Суперприз, руб.","value":"2 687 095,50"},{"name":"В архиве тиража отображается сумма суперприза на начало тиража, которая разыгрывалась в этом тираже.","value":""}]},{"drawTime":"2020070316523000","issue":"188475","jackpot":["2 351 236,50"],"numbers":"5,4,10,19,12,20,17,11|1","detail":[{"level":"8 + 1","total_winner":"0","wininrub":"0","numbersOfWinners":"0"},{"level":"8","total_winner":"0","wininrub":"0","numbersOfWinners":"0"},{"level":"7 + 1","total_winner":"67 500","wininrub":"22 500","numbersOfWinners":"3"},{"level":"7","total_winner":"7500","wininrub":"7500","numbersOfWinners":"1"},{"level":"6 + 1","total_winner":"13 500","wininrub":"4500","numbersOfWinners":"3"},{"level":"6","total_winner":"21 000","wininrub":"1500","numbersOfWinners":"14"},{"level":"5 + 1","total_winner":"34 500","wininrub":"750","numbersOfWinners":"46"},{"level":"5","total_winner":"47 100","wininrub":"300","numbersOfWinners":"157"},{"level":"4 + 1","total_winner":"19 650","wininrub":"150","numbersOfWinners":"131"}],"lotteryID":"ru-rapido","name":"rapido","other":[{"name":"Число билетов, принявших участие в розыгрыше,","value":"1864"},{"name":"Комбинаций","value":"2358"},{"name":"Общая сумма выигрышей, руб.","value":"210 750"},{"name":"Суперприз, руб.","value":"2 351 236,50"},{"name":"В архиве тиража отображается сумма суперприза на начало тиража, которая разыгрывалась в этом тираже.","value":""}]},{"drawTime":"2020070302073000","issue":"188425","jackpot":["1 767 292,50"],"numbers":"18,17,3,9,13,12,16,8|3","detail":[{"level":"8 + 1","total_winner":"0","wininrub":"0","numbersOfWinners":"0"},{"level":"8","total_winner":"0","wininrub":"0","numbersOfWinners":"0"},{"level":"7 + 1","total_winner":"0","wininrub":"0","numbersOfWinners":"0"},{"level":"7","total_winner":"30 000","wininrub":"7500","numbersOfWinners":"4"},{"level":"6 + 1","total_winner":"22 500","wininrub":"4500","numbersOfWinners":"5"},{"level":"6","total_winner":"15 000","wininrub":"1500","numbersOfWinners":"10"},{"level":"5 + 1","total_winner":"12 000","wininrub":"750","numbersOfWinners":"16"},{"level":"5","total_winner":"13 500","wininrub":"300","numbersOfWinners":"45"},{"level":"4 + 1","total_winner":"6150","wininrub":"150","numbersOfWinners":"41"}],"lotteryID":"ru-rapido","name":"rapido","other":[{"name":"Число билетов, принявших участие в розыгрыше,","value":"423"},{"name":"Комбинаций","value":"532"},{"name":"Общая сумма выигрышей, руб.","value":"99 150"},{"name":"Суперприз, руб.","value":"1 767 292,50"},{"name":"В архиве тиража отображается сумма суперприза на начало тиража, которая разыгрывалась в этом тираже.","value":""}]},{"drawTime":"2020070211223000","issue":"188375","jackpot":["977 029,50"],"numbers":"10,19,13,1,2,18,12,8|3","detail":[{"level":"8 + 1","total_winner":"0","wininrub":"0","numbersOfWinners":"0"},{"level":"8","total_winner":"0","wininrub":"0","numbersOfWinners":"0"},{"level":"7 + 1","total_winner":"0","wininrub":"0","numbersOfWinners":"0"},{"level":"7","total_winner":"7500","wininrub":"7500","numbersOfWinners":"1"},{"level":"6 + 1","total_winner":"54 000","wininrub":"4500","numbersOfWinners":"12"},{"level":"6","total_winner":"33 000","wininrub":"1500","numbersOfWinners":"22"},{"level":"5 + 1","total_winner":"31 500","wininrub":"750","numbersOfWinners":"42"},{"level":"5","total_winner":"35 100","wininrub":"300","numbersOfWinners":"117"},{"level":"4 + 1","total_winner":"17 850","wininrub":"150","numbersOfWinners":"119"}],"lotteryID":"ru-rapido","name":"rapido","other":[{"name":"Число билетов, принявших участие в розыгрыше,","value":"1312"},{"name":"Комбинаций","value":"1612"},{"name":"Общая сумма выигрышей, руб.","value":"178 950"},{"name":"Суперприз, руб.","value":"977 029,50"},{"name":"В архиве тиража отображается сумма суперприза на начало тиража, которая разыгрывалась в этом тираже.","value":""}]},{"drawTime":"2020070121223000","issue":"188325","jackpot":["421 816,50"],"numbers":"5,9,17,16,18,2,14,8|3","detail":[{"level":"8 + 1","total_winner":"0","wininrub":"0","numbersOfWinners":"0"},{"level":"8","total_winner":"0","wininrub":"0","numbersOfWinners":"0"},{"level":"7 + 1","total_winner":"0","wininrub":"0","numbersOfWinners":"0"},{"level":"7","total_winner":"45 000","wininrub":"7500","numbersOfWinners":"6"},{"level":"6 + 1","total_winner":"13 500","wininrub":"4500","numbersOfWinners":"3"},{"level":"6","total_winner":"24 000","wininrub":"1500","numbersOfWinners":"16"},{"level":"5 + 1","total_winner":"24 750","wininrub":"750","numbersOfWinners":"33"},{"level":"5","total_winner":"35 100","wininrub":"300","numbersOfWinners":"117"},{"level":"4 + 1","total_winner":"13 950","wininrub":"150","numbersOfWinners":"93"}],"lotteryID":"ru-rapido","name":"rapido","other":[{"name":"Число билетов, принявших участие в розыгрыше,","value":"996"},{"name":"Комбинаций","value":"1273"},{"name":"Общая сумма выигрышей, руб.","value":"156 300"},{"name":"Суперприз, руб.","value":"421 816,50"},{"name":"В архиве тиража отображается сумма суперприза на начало тиража, которая разыгрывалась в этом тираже.","value":""}]},{"drawTime":"2020070106373000","issue":"188275","jackpot":["200 000"],"numbers":"6,4,7,16,19,20,3,1|1","detail":[{"level":"8 + 1","total_winner":"0","wininrub":"0","numbersOfWinners":"0"},{"level":"8","total_winner":"0","wininrub":"0","numbersOfWinners":"0"},{"level":"7 + 1","total_winner":"0","wininrub":"0","numbersOfWinners":"0"},{"level":"7","total_winner":"0","wininrub":"0","numbersOfWinners":"0"},{"level":"6 + 1","total_winner":"13 500","wininrub":"4500","numbersOfWinners":"3"},{"level":"6","total_winner":"3000","wininrub":"1500","numbersOfWinners":"2"},{"level":"5 + 1","total_winner":"8250","wininrub":"750","numbersOfWinners":"11"},{"level":"5","total_winner":"9600","wininrub":"300","numbersOfWinners":"32"},{"level":"4 + 1","total_winner":"3900","wininrub":"150","numbersOfWinners":"26"}],"lotteryID":"ru-rapido","name":"rapido","other":[{"name":"Число билетов, принявших участие в розыгрыше,","value":"371"},{"name":"Комбинаций","value":"468"},{"name":"Общая сумма выигрышей, руб.","value":"38 250"},{"name":"Суперприз, руб.","value":"200 000"},{"name":"В архиве тиража отображается сумма суперприза на начало тиража, которая разыгрывалась в этом тираже.","value":""}]}]